mcp_jetbrains_proxy/__init__.py
mcp_jetbrains_proxy/__main__.py
mcp_jetbrains_proxy/_version.py
mcp_jetbrains_proxy/endpoint.py
mcp_jetbrains_proxy/logging.py
mcp_jetbrains_proxy/server.py
mcp_jetbrains_proxy-0.1.1.dev30.dist-info/METADATA
mcp_jetbrains_proxy-0.1.1.dev30.dist-info/WHEEL
mcp_jetbrains_proxy-0.1.1.dev30.dist-info/entry_points.txt
mcp_jetbrains_proxy-0.1.1.dev30.dist-info/licenses/LICENSE
mcp_jetbrains_proxy-0.1.1.dev30.dist-info/RECORD
